clickup_toolkit/__init__.py
clickup_toolkit/client.py
clickup_toolkit/errors.py
clickup_toolkit/models.py
clickup_toolkit-0.0.11.dist-info/METADATA
clickup_toolkit-0.0.11.dist-info/WHEEL
clickup_toolkit-0.0.11.dist-info/RECORD
